pytest_tm4j_reporter/__init__.py
pytest_tm4j_reporter/reporter.py
pytest_tm4j_reporter-0.1.2.dist-info/LICENSE
pytest_tm4j_reporter-0.1.2.dist-info/METADATA
pytest_tm4j_reporter-0.1.2.dist-info/WHEEL
pytest_tm4j_reporter-0.1.2.dist-info/entry_points.txt
pytest_tm4j_reporter-0.1.2.dist-info/top_level.txt
pytest_tm4j_reporter-0.1.2.dist-info/RECORD
