Metadata-Version: 2.1
Name: pytest-tm4j-reporter
Version: 0.1.2
Summary: Cloud Jira Test Management (TM4J) PyTest reporter plugin
Home-page: https://github.com/Klika-Tech/tm4j_reporter_pytest
Author: 
Author-email: contact@klika-tech.com
License: MIT
Keywords: python pytest tm4j jira test testmanagement report
Platform: any
Classifier: Framework :: Pytest
Classifier: Intended Audience :: Developers
Classifier: License :: OSI Approved :: MIT License
Classifier: Operating System :: OS Independent
Classifier: Programming Language :: Python :: 3
Classifier: Programming Language :: Python
Classifier: Topic :: Software Development :: Libraries :: Python Modules
Classifier: Topic :: Software Development :: Quality Assurance
Classifier: Topic :: Software Development :: Testing
Classifier: Topic :: Utilities
Requires-Python: >=3.6
Requires-Dist: pytest
Requires-Dist: pytest-json-report
Requires-Dist: tm4j-reporter-api (==0.1.1)
